telegram_util/__init__.py
telegram_util-0.0.167.dist-info/LICENSE
telegram_util-0.0.167.dist-info/METADATA
telegram_util-0.0.167.dist-info/WHEEL
telegram_util-0.0.167.dist-info/top_level.txt
telegram_util-0.0.167.dist-info/RECORD
