Metadata-Version: 2.1
Name: telegram-util
Version: 0.0.167
Summary: Telegram Util.
Home-page: https://github.com/gaoyunzhi/telegram_util
Author: Yunzhi Gao
Author-email: gaoyunzhi@gmail.com
License: UNKNOWN
Platform: UNKNOWN
Classifier: Programming Language :: Python :: 3
Classifier: License :: OSI Approved :: MIT License
Classifier: Operating System :: OS Independent
Requires-Python: >=3.0
License-File: LICENSE
Requires-Dist: bs4
Requires-Dist: pyyaml
